CHANGES.rst
CONTRIBUTORS.rst
MANIFEST.in
README.rst
setup.cfg
setup.py
docs/LICENSE.GPL
docs/LICENSE.txt
docs/controlpanel.png
docs/texttospeech.png
docs/viewlet.png
src/collective/__init__.py
src/collective.texttospeech.egg-info/PKG-INFO
src/collective.texttospeech.egg-info/SOURCES.txt
src/collective.texttospeech.egg-info/dependency_links.txt
src/collective.texttospeech.egg-info/entry_points.txt
src/collective.texttospeech.egg-info/namespace_packages.txt
src/collective.texttospeech.egg-info/not-zip-safe
src/collective.texttospeech.egg-info/requires.txt
src/collective.texttospeech.egg-info/top_level.txt
src/collective/texttospeech/__init__.py
src/collective/texttospeech/config.py
src/collective/texttospeech/configure.zcml
src/collective/texttospeech/controlpanel.py
src/collective/texttospeech/interfaces.py
src/collective/texttospeech/logger.py
src/collective/texttospeech/profiles.zcml
src/collective/texttospeech/setuphandlers.py
src/collective/texttospeech/testing.py
src/collective/texttospeech/Extensions/Install.py
src/collective/texttospeech/Extensions/__init__.py
src/collective/texttospeech/browser/__init__.py
src/collective/texttospeech/browser/configure.zcml
src/collective/texttospeech/browser/viewlets.py
src/collective/texttospeech/browser/templates/texttospeech.pt
src/collective/texttospeech/locales/collective.texttospeech.pot
src/collective/texttospeech/locales/manual.pot
src/collective/texttospeech/locales/plone.pot
src/collective/texttospeech/locales/es/LC_MESSAGES/collective.texttospeech.po
src/collective/texttospeech/locales/es/LC_MESSAGES/plone.po
src/collective/texttospeech/locales/pt_BR/LC_MESSAGES/collective.texttospeech.po
src/collective/texttospeech/locales/pt_BR/LC_MESSAGES/plone.po
src/collective/texttospeech/profiles/default/browserlayer.xml
src/collective/texttospeech/profiles/default/controlpanel.xml
src/collective/texttospeech/profiles/default/cssregistry.xml
src/collective/texttospeech/profiles/default/jsregistry.xml
src/collective/texttospeech/profiles/default/metadata.xml
src/collective/texttospeech/profiles/default/registry.xml
src/collective/texttospeech/profiles/default/rolemap.xml
src/collective/texttospeech/profiles/uninstall/registry.xml
src/collective/texttospeech/static/file-audio-o.svg
src/collective/texttospeech/static/main.css
src/collective/texttospeech/static/main.js
src/collective/texttospeech/static/texttospeech-icon.png
