Metadata-Version: 1.1
Name: collective.texttospeech
Version: 1.0b2
Summary: Text-to-Speech feature for Plone.
Home-page: https://github.com/collective/collective.texttospeech
Author: Simples Consultoria
Author-email: produtos@simplesconsultoria.com.br
License: UNKNOWN
Platform: UNKNOWN
Classifier: Development Status :: 4 - Beta
Classifier: Environment :: Web Environment
Classifier: Framework :: Plone
Classifier: Framework :: Plone :: 4.3
Classifier: Framework :: Plone :: 5.0
Classifier: Intended Audience :: System Administrators
Classifier: License :: OSI Approved :: GNU General Public License v2 (GPLv2)
Classifier: Operating System :: OS Independent
Classifier: Programming Language :: Python
Classifier: Programming Language :: Python :: 2.7
Classifier: Topic :: Software Development :: Libraries :: Python Modules
